hello_message/__init__.py
hello_message/hello.py
hello_message_sdk-0.3.0.dist-info/LICENSE
hello_message_sdk-0.3.0.dist-info/METADATA
hello_message_sdk-0.3.0.dist-info/WHEEL
hello_message_sdk-0.3.0.dist-info/top_level.txt
hello_message_sdk-0.3.0.dist-info/RECORD
