Metadata-Version: 2.1
Name: hello-message-sdk
Version: 0.3.0
Summary: A Python SDK for AI agents to securely generate and verify 'hello' authentication messages, enabling seamless interaction between AI agents and AI-centric services.
Home-page: https://github.com/aimxlabs/hello-message-python
Author: anythingmachine
Author-email: anythingmachine@aimx.com
Keywords: hello-message,authentication,ethereum,sdk,ai,artificial-intelligence,autonomous-agents,ai-first-services,blockchain,ai-authentication
Classifier: Programming Language :: Python :: 3
Classifier: Programming Language :: Python :: 3.6
Classifier: Programming Language :: Python :: 3.7
Classifier: Programming Language :: Python :: 3.8
Classifier: Programming Language :: Python :: 3.9
Classifier: Programming Language :: Python :: 3.10
Classifier: License :: OSI Approved :: MIT License
Classifier: Operating System :: OS Independent
Requires-Python: >=3.6
License-File: LICENSE
Requires-Dist: eth-account>=0.13.4
Provides-Extra: dev
Requires-Dist: pytest; extra == "dev"
